gitcoin/__init__.py
gitcoin/client.py
gitcoin/validation.py
gitcoin-0.1.0.dist-info/LICENSE.txt
gitcoin-0.1.0.dist-info/METADATA
gitcoin-0.1.0.dist-info/RECORD
gitcoin-0.1.0.dist-info/WHEEL
gitcoin-0.1.0.dist-info/top_level.txt
