Metadata-Version: 2.1
Name: gitcoin
Version: 0.1.0
Summary: The Gitcoin.co python API client
Home-page: https://github.com/gitcoinco/python-api-client
Author: Gitcoin
Author-email: team@gitcoin.co
License: UNKNOWN
Project-URL: Bug Reports, https://github.com/gitcoinco/python-api-client/issues
Project-URL: Homepage, https://gitcoin.co
Project-URL: Source, https://github.com/gitcoinco/python-api-client/
Project-URL: API Project, https://github.com/gitcoinco/web
Keywords: gitcoin api client bounties bounty rest
Platform: UNKNOWN
Classifier: Development Status :: 3 - Alpha
Classifier: Intended Audience :: Developers
Classifier: Topic :: Software Development
Classifier: Topic :: Software Development :: Libraries
Classifier: Topic :: Software Development :: Libraries :: Python Modules
Classifier: Topic :: Software Development :: Build Tools
Classifier: License :: OSI Approved :: GNU Affero General Public License v3
Classifier: Programming Language :: Python :: 3
Classifier: Programming Language :: Python :: 3.5
Classifier: Programming Language :: Python :: 3.6
Classifier: Programming Language :: Python :: 3.7
Classifier: Programming Language :: Python :: 3 :: Only
Classifier: Natural Language :: English
Requires-Python: ~=3.5
Provides-Extra: deploy
Requires-Dist: requests
Provides-Extra: deploy
Requires-Dist: twine; extra == 'deploy'
Requires-Dist: wheel; extra == 'deploy'
